Paginator.py
dpy_container_pagination-0.1.1.dist-info/licenses/LICENSE
dpy_container_pagination-0.1.1.dist-info/METADATA
dpy_container_pagination-0.1.1.dist-info/WHEEL
dpy_container_pagination-0.1.1.dist-info/top_level.txt
dpy_container_pagination-0.1.1.dist-info/RECORD
